okta_uuid.py
okta_uuid-0.1.0.dist-info/METADATA
okta_uuid-0.1.0.dist-info/RECORD
okta_uuid-0.1.0.dist-info/WHEEL
okta_uuid-0.1.0.dist-info/top_level.txt
