Metadata-Version: 2.1
Name: okta-uuid
Version: 0.1.0
Summary: Turn Okta User IDs into UUIDs.
Home-page: https://github.com/tmehlinger/okta-uuid
Author: Travis Mehlinger
Author-email: tmehlinger@gmail.com
License: MIT
Keywords: okta uuid
Platform: UNKNOWN
Classifier: Development Status :: 4 - Beta
Classifier: Intended Audience :: Developers
Classifier: License :: OSI Approved :: MIT License
Classifier: Programming Language :: Python :: 3
Classifier: Programming Language :: Python :: 3.3
Classifier: Programming Language :: Python :: 3.4
Classifier: Programming Language :: Python :: 3.5
Classifier: Programming Language :: Python :: 3.6
Requires-Dist: pybase62
